penguins_pytest_docker-0.0.7-py3.7-nspkg.pth
lovely/pytest/__init__.py
lovely/pytest/docker/__init__.py
lovely/pytest/docker/compose.py
penguins_pytest_docker-0.0.7.dist-info/LICENSE.txt
penguins_pytest_docker-0.0.7.dist-info/METADATA
penguins_pytest_docker-0.0.7.dist-info/WHEEL
penguins_pytest_docker-0.0.7.dist-info/entry_points.txt
penguins_pytest_docker-0.0.7.dist-info/namespace_packages.txt
penguins_pytest_docker-0.0.7.dist-info/top_level.txt
penguins_pytest_docker-0.0.7.dist-info/RECORD
