Metadata-Version: 2.1
Name: penguins-pytest-docker
Version: 0.0.7
Summary: Pytest testing utilities with docker containers.
Home-page: https://github.com/angry-penguins/lovely-pytest-docker
Author: zgallerie
Author-email: developers@directbuy.com
License: UNKNOWN
Keywords: pytest testing docker compose
Platform: UNKNOWN
Classifier: Programming Language :: Python :: 3
Classifier: Programming Language :: Python :: 2.7
Requires-Dist: pytest
